{
  "id": "M07",
  "title": "Ganzzahlige Optimierung & Heuristiken (v3) – Prüfungsset E/F",
  "description": "Zusätzliche prüfungsnahe Rechenaufgaben mit gestuften Hinweisen (Sets E und F) in allen vier Lessons.",
  "lessons": [
    {
      "id": "M07L01",
      "title": "Ganzzahlige Modelle I – Prüfungsset E/F (Rechen‑Mix mit gestuften Hinweisen)"
    },
    {
      "id": "M07L02",
      "title": "Ganzzahlige Modelle II – B&B: Prüfungsset E/F (Rechen‑Mix + gestufte Hinweise)"
    },
    {
      "id": "M07L03",
      "title": "Klassische MILP‑Probleme – Prüfungsset E/F (Rechen‑Mix + gestufte Hinweise)"
    },
    {
      "id": "M07L04",
      "title": "Heuristiken & Metaheuristiken – Prüfungsset E/F (Rechen‑Mix + gestufte Hinweise)"
    }
  ],
  "version": "v3",
  "updated_at": "2025-08-17T09:33:18.738480"
}