{
  "chapter": {
    "id": "M02",
    "title": "Übungen M02",
    "title_segments": [
      {
        "t": "text",
        "text": "Übungen M02"
      }
    ]
  },
  "sections": [
    {
      "id": "uebung-mix",
      "title": "Prozent- & einfache Zinsrechnung",
      "title_segments": [
        {
          "t": "text",
          "text": "Prozent- & einfache Zinsrechnung"
        }
      ],
      "file": "exercises/M02/uebung-mix/module.json"
    }
  ],
  "meta": {
    "schema_version": "mtb.v2",
    "locale": "de-DE",
    "math": {
      "decimal_comma": true,
      "macros": {
        "\\euro": "\\text{€}"
      }
    },
    "formatting": {
      "currency": "€ {amount},-",
      "thousand_sep": ".",
      "decimal_sep": ","
    }
  }
}